pymyanlp/__init__.py
pymyanlp/analysis/grammer.py
pymyanlp/analysis/sentiment.py
pymyanlp/analysis/spellcheck.py
pymyanlp/lib/mypos/__init__.py
pymyanlp/lib/mypos/RDRPOSTagger/api.py
pymyanlp/lib/mypos/RDRPOSTagger/InitialTagger/InitialTagger.py
pymyanlp/lib/mypos/RDRPOSTagger/InitialTagger/InitialTagger4En.py
pymyanlp/lib/mypos/RDRPOSTagger/InitialTagger/InitialTagger4Vn.py
pymyanlp/lib/mypos/RDRPOSTagger/InitialTagger/__init__.py
pymyanlp/lib/mypos/RDRPOSTagger/SCRDRlearner/Node.py
pymyanlp/lib/mypos/RDRPOSTagger/SCRDRlearner/Object.py
pymyanlp/lib/mypos/RDRPOSTagger/SCRDRlearner/SCRDRTree.py
pymyanlp/lib/mypos/RDRPOSTagger/SCRDRlearner/SCRDRTreeLearner.py
pymyanlp/lib/mypos/RDRPOSTagger/SCRDRlearner/__init__.py
pymyanlp/lib/mypos/RDRPOSTagger/Utility/Config.py
pymyanlp/lib/mypos/RDRPOSTagger/Utility/Eval.py
pymyanlp/lib/mypos/RDRPOSTagger/Utility/LexiconCreator.py
pymyanlp/lib/mypos/RDRPOSTagger/Utility/Utils.py
pymyanlp/lib/mypos/RDRPOSTagger/Utility/__init__.py
pymyanlp/lib/mypos/RDRPOSTagger/pSCRDRtagger/ExtRDRPOSTagger.py
pymyanlp/lib/mypos/RDRPOSTagger/pSCRDRtagger/RDRPOSTagger.py
pymyanlp/lib/mypos/RDRPOSTagger/pSCRDRtagger/RDRPOSTagger4En.py
pymyanlp/lib/mypos/RDRPOSTagger/pSCRDRtagger/RDRPOSTagger4Vn.py
pymyanlp/lib/mypos/RDRPOSTagger/pSCRDRtagger/__init__.py
pymyanlp/lib/mypos/models/v3_train1.nopipe.DICT
pymyanlp/lib/mypos/models/v3_train1.nopipe.RDR
pymyanlp/lib/myword/__init__.py
pymyanlp/lib/myword/models/bigram-word.bin
pymyanlp/lib/myword/models/unigram-word.bin
pymyanlp/resources/keywords.py
pymyanlp/resources/stopword.py
pymyanlp/text/pos.py
pymyanlp/text/script.py
pymyanlp/text/segment.py
pymyanlp/text/style.py
pymyanlp/text/tokenizer.py
pymyanlp-0.1.1.dist-info/licenses/LICENSE.txt
pymyanlp-0.1.1.dist-info/METADATA
pymyanlp-0.1.1.dist-info/WHEEL
pymyanlp-0.1.1.dist-info/top_level.txt
pymyanlp-0.1.1.dist-info/RECORD
