Metadata-Version: 2.4
Name: pymyanlp
Version: 0.1.1
Summary: Python utilities for Myanmar language processing
Author: Pyae Sone Myo
License-Expression: MIT
Project-URL: Homepage, https://github.com/Rickaym/pymyanlp
Project-URL: Bug Tracker, https://github.com/Rickaym/pymyanlp/issues
Classifier: Development Status :: 3 - Alpha
Classifier: Intended Audience :: Developers
Classifier: Programming Language :: Python :: 3
Classifier: Programming Language :: Python :: 3.7
Classifier: Programming Language :: Python :: 3.8
Classifier: Programming Language :: Python :: 3.9
Classifier: Programming Language :: Python :: 3.10
Classifier: Programming Language :: Python :: 3.11
Classifier: Topic :: Text Processing :: Linguistic
Requires-Python: >=3.7
License-File: LICENSE.txt
Requires-Dist: numpy>=1.21.6
Requires-Dist: pandas>=1.1.5
Requires-Dist: pyenchant>=3.2.2
Requires-Dist: symspellpy>=6.7.7
Dynamic: license-file
